open_gpts/__init__.py
open_gpts/adapter.py
open_gpts/executor.py
open_gpts/factory.py
open_gpts/helper.py
open_gpts/hub.py
open_gpts/logging.py
open_gpts/models/__init__.py
open_gpts/models/flamingo/__init__.py
open_gpts/models/flamingo/flamingo_lm.py
open_gpts/models/flamingo/loading.py
open_gpts/models/flamingo/modeling.py
open_gpts/models/flan/__init__.py
open_gpts/models/flan/loading.py
open_gpts/models/hf_model.py
open_gpts/models/llama/__init__.py
open_gpts/models/llama/loading.py
open_gpts/models/pythia/__init__.py
open_gpts/models/pythia/loading.py
open_gpts/profile.py
open_gpts/serve.py
open_gpts-0.0.1rc1.dist-info/LICENSE
open_gpts-0.0.1rc1.dist-info/METADATA
open_gpts-0.0.1rc1.dist-info/WHEEL
open_gpts-0.0.1rc1.dist-info/RECORD
