Metadata-Version: 2.1
Name: open-gpts
Version: 0.0.1rc1
Summary: An open-source implementation of large-scale language model (LLM).
Home-page: https://open-gpt.jina.ai
License: Apache-2.0
Keywords: Pytorch,LLM,GPT
Author: Felix Wang
Author-email: felix.wang@jina.ai
Requires-Python: >=3.8
Classifier: License :: OSI Approved :: Apache Software License
Classifier: Programming Language :: Python :: 3
Classifier: Programming Language :: Python :: 3.8
Classifier: Programming Language :: Python :: 3.9
Classifier: Programming Language :: Python :: 3.10
Classifier: Programming Language :: Python :: 3.11
Classifier: Programming Language :: Python :: 3
Classifier: Programming Language :: Python :: 3.10
Classifier: Programming Language :: Python :: 3.11
Classifier: Programming Language :: Python :: 3.7
Classifier: Programming Language :: Python :: 3.8
Classifier: Programming Language :: Python :: 3.9
Provides-Extra: flamingo
Requires-Dist: accelerate (>=0.18.0,<0.19.0)
Requires-Dist: click (>=8.1.3,<9.0.0)
Requires-Dist: einops (>=0.6.0,<0.7.0)
Requires-Dist: loguru (>=0.5,<0.6)
Requires-Dist: numpy (>=1.21.2,<2.0.0)
Requires-Dist: open-flamingo (>=0.0,<0.1) ; extra == "flamingo"
Requires-Dist: open_clip_torch (>=2.16.0,<2.17.0)
Requires-Dist: torch (>=1.9.0,<2.0.0)
Requires-Dist: transformers (>=4.12.5,<5.0.0)
Project-URL: Repository, https://github.com/jina-ai/open_gpt
